myautoml/__about__.py
myautoml/__init__.py
myautoml/cli.py
myautoml/calibration/__init__.py
myautoml/evaluation/__init__.py
myautoml/evaluation/binary_classifier.py
myautoml/evaluation/shap.py
myautoml/utils/__init__.py
myautoml/utils/cache.py
myautoml/utils/default_config.yml
myautoml/utils/hyperopt.py
myautoml/utils/logger.py
myautoml/utils/model.py
myautoml/utils/pickle.py
myautoml/utils/sklearn.py
myautoml/utils/mlflow/__init__.py
myautoml/utils/mlflow/models.py
myautoml/utils/mlflow/tracking.py
myautoml/visualisation/__init__.py
myautoml/visualisation/colors.py
myautoml/visualisation/evaluation/__init__.py
myautoml/visualisation/evaluation/binary_classifier.py
myautoml/visualisation/evaluation/shap.py
myautoml-0.6.2.dist-info/METADATA
myautoml-0.6.2.dist-info/WHEEL
myautoml-0.6.2.dist-info/entry_points.txt
myautoml-0.6.2.dist-info/top_level.txt
myautoml-0.6.2.dist-info/RECORD
