Metadata-Version: 2.1
Name: myautoml
Version: 0.6.2
Summary: myautoml is a package which provides a framework to automate machine learning
Home-page: https://github.com/myautoml/myautoml
Author: Erik Jan de Vries
License: UNKNOWN
Project-URL: Documentation, https://myautoml.readthedocs.io
Project-URL: Source Code, https://github.com/myautoml/myautoml
Platform: UNKNOWN
Classifier: Intended Audience :: Developers
Classifier: Programming Language :: Python :: 3
Classifier: Operating System :: OS Independent
Requires-Python: >=3.8
Requires-Dist: click
Requires-Dist: joblib
Requires-Dist: mlflow
Requires-Dist: numpy
Requires-Dist: pandas
Requires-Dist: pyyaml
Requires-Dist: scikit-learn
Requires-Dist: python-box
Requires-Dist: python-dotenv
Requires-Dist: envyaml
Provides-Extra: all
Requires-Dist: shap ; extra == 'all'
Requires-Dist: hyperopt ; extra == 'all'
Requires-Dist: mlflow ; extra == 'all'
Requires-Dist: matplotlib ; extra == 'all'
Requires-Dist: seaborn ; extra == 'all'
Provides-Extra: evaluation
Requires-Dist: shap ; extra == 'evaluation'
Provides-Extra: optimisation
Requires-Dist: hyperopt ; extra == 'optimisation'
Provides-Extra: tracking
Requires-Dist: mlflow ; extra == 'tracking'
Provides-Extra: visualisation
Requires-Dist: matplotlib ; extra == 'visualisation'
Requires-Dist: seaborn ; extra == 'visualisation'
